py_ssdb_client/__init__.py
py_ssdb_client/base_ssdb.py
py_ssdb_client/ssdb_client.py
py_ssdb_client/ssdb_hash.py
py_ssdb_client/ssdb_kv.py
py_ssdb_client/ssdb_sorted_set.py
py_ssdb_client/utils.py
py_ssdb_client-0.1.7.dist-info/LICENSE
py_ssdb_client-0.1.7.dist-info/METADATA
py_ssdb_client-0.1.7.dist-info/WHEEL
py_ssdb_client-0.1.7.dist-info/top_level.txt
py_ssdb_client-0.1.7.dist-info/RECORD
